MANIFEST.in
README
setup.py
createApGui/__init__.py
createApGui/__main__.py
createApGui/aboutPage.py
createApGui/createPage.py
createApGui/editPage.py
createApGui/gui.py
createApGui/guiComponent.py
createApGui/language.py
createApGui/mainWindow.py
createApGui/runningAp.py
createApGui/settingPage.py
createApGui/statusPage.py
createApGui/terminalInterface.py
createApGui/trayIcon.py
createApGui/trayRightClickMenu.py
createApGui/userSetting.py
createApGui/image/icon.png
createApGui/lang/Czech_cs/LC_MESSAGES/lang.mo
createApGui/lang/Czech_cs/LC_MESSAGES/lang.po
createApGui/lang/English_en/LC_MESSAGES/lang.mo
createApGui/lang/English_en/LC_MESSAGES/lang.po
create_ap_gui.egg-info/PKG-INFO
create_ap_gui.egg-info/SOURCES.txt
create_ap_gui.egg-info/dependency_links.txt
create_ap_gui.egg-info/entry_points.txt
create_ap_gui.egg-info/top_level.txt
postinst/createApGui.desktop
postinst/createApGui.png