Metadata-Version: 1.1
Name: create-ap-gui
Version: 1.3.1
Summary: Easy create Access point
Home-page: -
Author: Jakub Pelikan
Author-email: jakub.pelikan@gmail.com
License: UNKNOWN
Keywords: AP,gui,access point
Platform: UNKNOWN
Classifier: Programming Language :: Python :: 3
Classifier: Operating System :: POSIX :: Linux
Classifier: Development Status :: 3 - Alpha
Classifier: License :: OSI Approved :: GNU General Public License v3 (GPLv3)
